{
  "$schema": "https://tree-sitter.github.io/tree-sitter/assets/schemas/grammar.schema.json",
  "name": "mest",
  "word": "identifier",
  "rules": {
    "source_file": {
      "type": "SYMBOL",
      "name": "expression"
    },
    "expression": {
      "type": "CHOICE",
      "members": [
        {
          "type": "SYMBOL",
          "name": "if_expression"
        },
        {
          "type": "SYMBOL",
          "name": "let_expression"
        },
        {
          "type": "SYMBOL",
          "name": "match_expression"
        },
        {
          "type": "SYMBOL",
          "name": "lambda_expression"
        },
        {
          "type": "SYMBOL",
          "name": "simple_expression"
        }
      ]
    },
    "simple_expression": {
      "type": "SYMBOL",
      "name": "or_expression"
    },
    "if_expression": {
      "type": "SEQ",
      "members": [
        {
          "type": "STRING",
          "value": "if"
        },
        {
          "type": "FIELD",
          "name": "condition",
          "content": {
            "type": "SYMBOL",
            "name": "expression"
          }
        },
        {
          "type": "STRING",
          "value": "then"
        },
        {
          "type": "FIELD",
          "name": "consequence",
          "content": {
            "type": "SYMBOL",
            "name": "expression"
          }
        },
        {
          "type": "STRING",
          "value": "else"
        },
        {
          "type": "FIELD",
          "name": "alternative",
          "content": {
            "type": "SYMBOL",
            "name": "expression"
          }
        }
      ]
    },
    "let_expression": {
      "type": "SEQ",
      "members": [
        {
          "type": "STRING",
          "value": "let"
        },
        {
          "type": "CHOICE",
          "members": [
            {
              "type": "STRING",
              "value": "rec"
            },
            {
              "type": "BLANK"
            }
          ]
        },
        {
          "type": "FIELD",
          "name": "name",
          "content": {
            "type": "SYMBOL",
            "name": "identifier"
          }
        },
        {
          "type": "REPEAT",
          "content": {
            "type": "FIELD",
            "name": "parameter",
            "content": {
              "type": "SYMBOL",
              "name": "identifier"
            }
          }
        },
        {
          "type": "STRING",
          "value": "="
        },
        {
          "type": "FIELD",
          "name": "value",
          "content": {
            "type": "SYMBOL",
            "name": "expression"
          }
        },
        {
          "type": "STRING",
          "value": "in"
        },
        {
          "type": "FIELD",
          "name": "body",
          "content": {
            "type": "SYMBOL",
            "name": "expression"
          }
        }
      ]
    },
    "match_expression": {
      "type": "PREC_RIGHT",
      "value": 0,
      "content": {
        "type": "SEQ",
        "members": [
          {
            "type": "STRING",
            "value": "match"
          },
          {
            "type": "FIELD",
            "name": "value",
            "content": {
              "type": "SYMBOL",
              "name": "simple_expression"
            }
          },
          {
            "type": "REPEAT1",
            "content": {
              "type": "SYMBOL",
              "name": "match_arm"
            }
          }
        ]
      }
    },
    "match_arm": {
      "type": "SEQ",
      "members": [
        {
          "type": "STRING",
          "value": "|"
        },
        {
          "type": "FIELD",
          "name": "pattern",
          "content": {
            "type": "SYMBOL",
            "name": "pattern"
          }
        },
        {
          "type": "STRING",
          "value": "=>"
        },
        {
          "type": "FIELD",
          "name": "body",
          "content": {
            "type": "SYMBOL",
            "name": "expression"
          }
        }
      ]
    },
    "lambda_expression": {
      "type": "SEQ",
      "members": [
        {
          "type": "STRING",
          "value": "|"
        },
        {
          "type": "FIELD",
          "name": "parameter",
          "content": {
            "type": "SYMBOL",
            "name": "identifier"
          }
        },
        {
          "type": "STRING",
          "value": "|"
        },
        {
          "type": "FIELD",
          "name": "body",
          "content": {
            "type": "SYMBOL",
            "name": "expression"
          }
        }
      ]
    },
    "or_expression": {
      "type": "PREC_LEFT",
      "value": 1,
      "content": {
        "type": "SEQ",
        "members": [
          {
            "type": "SYMBOL",
            "name": "and_expression"
          },
          {
            "type": "REPEAT",
            "content": {
              "type": "SEQ",
              "members": [
                {
                  "type": "STRING",
                  "value": "||"
                },
                {
                  "type": "SYMBOL",
                  "name": "and_expression"
                }
              ]
            }
          }
        ]
      }
    },
    "and_expression": {
      "type": "PREC_LEFT",
      "value": 2,
      "content": {
        "type": "SEQ",
        "members": [
          {
            "type": "SYMBOL",
            "name": "comparison_expression"
          },
          {
            "type": "REPEAT",
            "content": {
              "type": "SEQ",
              "members": [
                {
                  "type": "STRING",
                  "value": "&&"
                },
                {
                  "type": "SYMBOL",
                  "name": "comparison_expression"
                }
              ]
            }
          }
        ]
      }
    },
    "comparison_expression": {
      "type": "PREC_LEFT",
      "value": 3,
      "content": {
        "type": "SEQ",
        "members": [
          {
            "type": "SYMBOL",
            "name": "additive_expression"
          },
          {
            "type": "REPEAT",
            "content": {
              "type": "SEQ",
              "members": [
                {
                  "type": "CHOICE",
                  "members": [
                    {
                      "type": "STRING",
                      "value": "=="
                    },
                    {
                      "type": "STRING",
                      "value": "!="
                    },
                    {
                      "type": "STRING",
                      "value": "<"
                    },
                    {
                      "type": "STRING",
                      "value": ">"
                    },
                    {
                      "type": "STRING",
                      "value": "<="
                    },
                    {
                      "type": "STRING",
                      "value": ">="
                    }
                  ]
                },
                {
                  "type": "SYMBOL",
                  "name": "additive_expression"
                }
              ]
            }
          }
        ]
      }
    },
    "additive_expression": {
      "type": "PREC_LEFT",
      "value": 4,
      "content": {
        "type": "SEQ",
        "members": [
          {
            "type": "SYMBOL",
            "name": "multiplicative_expression"
          },
          {
            "type": "REPEAT",
            "content": {
              "type": "SEQ",
              "members": [
                {
                  "type": "CHOICE",
                  "members": [
                    {
                      "type": "STRING",
                      "value": "+"
                    },
                    {
                      "type": "STRING",
                      "value": "-"
                    }
                  ]
                },
                {
                  "type": "SYMBOL",
                  "name": "multiplicative_expression"
                }
              ]
            }
          }
        ]
      }
    },
    "multiplicative_expression": {
      "type": "PREC_LEFT",
      "value": 5,
      "content": {
        "type": "SEQ",
        "members": [
          {
            "type": "SYMBOL",
            "name": "power_expression"
          },
          {
            "type": "REPEAT",
            "content": {
              "type": "SEQ",
              "members": [
                {
                  "type": "CHOICE",
                  "members": [
                    {
                      "type": "STRING",
                      "value": "*"
                    },
                    {
                      "type": "STRING",
                      "value": "/"
                    }
                  ]
                },
                {
                  "type": "SYMBOL",
                  "name": "power_expression"
                }
              ]
            }
          }
        ]
      }
    },
    "power_expression": {
      "type": "PREC_RIGHT",
      "value": 6,
      "content": {
        "type": "SEQ",
        "members": [
          {
            "type": "SYMBOL",
            "name": "prefix_expression"
          },
          {
            "type": "CHOICE",
            "members": [
              {
                "type": "SEQ",
                "members": [
                  {
                    "type": "STRING",
                    "value": "^"
                  },
                  {
                    "type": "SYMBOL",
                    "name": "power_expression"
                  }
                ]
              },
              {
                "type": "BLANK"
              }
            ]
          }
        ]
      }
    },
    "prefix_expression": {
      "type": "CHOICE",
      "members": [
        {
          "type": "SYMBOL",
          "name": "not_expression"
        },
        {
          "type": "SYMBOL",
          "name": "negative_expression"
        },
        {
          "type": "SYMBOL",
          "name": "call_expression"
        },
        {
          "type": "SYMBOL",
          "name": "atom"
        }
      ]
    },
    "not_expression": {
      "type": "PREC_RIGHT",
      "value": 7,
      "content": {
        "type": "SEQ",
        "members": [
          {
            "type": "REPEAT1",
            "content": {
              "type": "STRING",
              "value": "!"
            }
          },
          {
            "type": "CHOICE",
            "members": [
              {
                "type": "SYMBOL",
                "name": "negative_expression"
              },
              {
                "type": "SYMBOL",
                "name": "call_expression"
              },
              {
                "type": "SYMBOL",
                "name": "atom"
              }
            ]
          }
        ]
      }
    },
    "negative_expression": {
      "type": "PREC_RIGHT",
      "value": 7,
      "content": {
        "type": "SEQ",
        "members": [
          {
            "type": "REPEAT1",
            "content": {
              "type": "STRING",
              "value": "-"
            }
          },
          {
            "type": "CHOICE",
            "members": [
              {
                "type": "SYMBOL",
                "name": "call_expression"
              },
              {
                "type": "SYMBOL",
                "name": "atom"
              }
            ]
          }
        ]
      }
    },
    "call_expression": {
      "type": "PREC_LEFT",
      "value": 8,
      "content": {
        "type": "SEQ",
        "members": [
          {
            "type": "SYMBOL",
            "name": "atom"
          },
          {
            "type": "REPEAT1",
            "content": {
              "type": "SYMBOL",
              "name": "atom"
            }
          }
        ]
      }
    },
    "atom": {
      "type": "CHOICE",
      "members": [
        {
          "type": "SYMBOL",
          "name": "identifier"
        },
        {
          "type": "SYMBOL",
          "name": "integer"
        },
        {
          "type": "SYMBOL",
          "name": "float"
        },
        {
          "type": "SYMBOL",
          "name": "boolean"
        },
        {
          "type": "SEQ",
          "members": [
            {
              "type": "STRING",
              "value": "("
            },
            {
              "type": "SYMBOL",
              "name": "expression"
            },
            {
              "type": "STRING",
              "value": ")"
            }
          ]
        }
      ]
    },
    "pattern": {
      "type": "CHOICE",
      "members": [
        {
          "type": "SYMBOL",
          "name": "wildcard_pattern"
        },
        {
          "type": "SYMBOL",
          "name": "literal"
        },
        {
          "type": "SYMBOL",
          "name": "identifier"
        }
      ]
    },
    "literal": {
      "type": "CHOICE",
      "members": [
        {
          "type": "SYMBOL",
          "name": "integer"
        },
        {
          "type": "SYMBOL",
          "name": "float"
        },
        {
          "type": "SYMBOL",
          "name": "boolean"
        }
      ]
    },
    "wildcard_pattern": {
      "type": "STRING",
      "value": "_"
    },
    "identifier": {
      "type": "PATTERN",
      "value": "[a-zA-Z_][a-zA-Z0-9_]*"
    },
    "integer": {
      "type": "TOKEN",
      "content": {
        "type": "PATTERN",
        "value": "[0-9]+"
      }
    },
    "float": {
      "type": "TOKEN",
      "content": {
        "type": "PATTERN",
        "value": "[0-9]+\\.[0-9]+"
      }
    },
    "boolean": {
      "type": "CHOICE",
      "members": [
        {
          "type": "STRING",
          "value": "true"
        },
        {
          "type": "STRING",
          "value": "false"
        }
      ]
    }
  },
  "extras": [
    {
      "type": "PATTERN",
      "value": "\\s"
    }
  ],
  "conflicts": [],
  "precedences": [],
  "externals": [],
  "inline": [],
  "supertypes": [],
  "reserved": {}
}